[
    {
        "date": "2023/8/31",
        "lastEpoch": "2023/8/30",
        "return": "  -   ",
        "cum_rtn": "  -   ",
        "rates": "6.43%",
        "TTM_Days": 667,
        "LastEpoch_Days": 668,
        "Price": 0.10772,
        "Cumulative_Price": 0.10772
    },
    {
        "date": "2023/9/1",
        "lastEpoch": "2023/9/1",
        "return": "  0.000411 ",
        "cum_rtn": "  0.000411 ",
        "rates": "6.59%",
        "TTM_Days": 666,
        "LastEpoch_Days": 666,
        "Price": 0.109968,
        "Cumulative_Price": 0.110379
    },
    {
        "date": "2023/9/2",
        "lastEpoch": "2023/9/1",
        "return": "  -   ",
        "cum_rtn": "  0.000411 ",
        "rates": "6.56%",
        "TTM_Days": 665,
        "LastEpoch_Days": 666,
        "Price": 0.109514,
        "Cumulative_Price": 0.109925
    },
    {
        "date": "2023/9/3",
        "lastEpoch": "2023/9/3",
        "return": "  0.000406 ",
        "cum_rtn": "  0.000817 ",
        "rates": "6.47%",
        "TTM_Days": 664,
        "LastEpoch_Days": 664,
        "Price": 0.107844,
        "Cumulative_Price": 0.108661
    },
    {
        "date": "2023/9/4",
        "lastEpoch": "2023/9/3",
        "return": "  -   ",
        "cum_rtn": "  0.000817 ",
        "rates": "6.61%",
        "TTM_Days": 663,
        "LastEpoch_Days": 664,
        "Price": 0.10991,
        "Cumulative_Price": 0.110727
    },
    {
        "date": "2023/9/5",
        "lastEpoch": "2023/9/5",
        "return": "  0.000405 ",
        "cum_rtn": "  0.001222 ",
        "rates": "6.71%",
        "TTM_Days": 662,
        "LastEpoch_Days": 662,
        "Price": 0.111068,
        "Cumulative_Price": 0.11229
    },
    {
        "date": "2023/9/6",
        "lastEpoch": "2023/9/5",
        "return": "  -   ",
        "cum_rtn": "  0.001222 ",
        "rates": "6.72%",
        "TTM_Days": 661,
        "LastEpoch_Days": 662,
        "Price": 0.111318,
        "Cumulative_Price": 0.11254
    },
    {
        "date": "2023/9/7",
        "lastEpoch": "2023/9/7",
        "return": "  0.000405 ",
        "cum_rtn": "  0.001627 ",
        "rates": "6.51%",
        "TTM_Days": 660,
        "LastEpoch_Days": 660,
        "Price": 0.107824,
        "Cumulative_Price": 0.109451
    },
    {
        "date": "2023/9/8",
        "lastEpoch": "2023/9/7",
        "return": "  -   ",
        "cum_rtn": "  0.001627 ",
        "rates": "6.57%",
        "TTM_Days": 659,
        "LastEpoch_Days": 660,
        "Price": 0.108739,
        "Cumulative_Price": 0.110367
    },
    {
        "date": "2023/9/9",
        "lastEpoch": "2023/9/7",
        "return": "  -   ",
        "cum_rtn": "  0.001627 ",
        "rates": "6.61%",
        "TTM_Days": 658,
        "LastEpoch_Days": 660,
        "Price": 0.109339,
        "Cumulative_Price": 0.110967
    },
    {
        "date": "2023/9/10",
        "lastEpoch": "2023/9/10",
        "return": "  0.000403 ",
        "cum_rtn": "  0.002031 ",
        "rates": "6.72%",
        "TTM_Days": 657,
        "LastEpoch_Days": 657,
        "Price": 0.1105,
        "Cumulative_Price": 0.112531
    },
    {
        "date": "2023/9/11",
        "lastEpoch": "2023/9/10",
        "return": "  -   ",
        "cum_rtn": "  0.002031 ",
        "rates": "6.58%",
        "TTM_Days": 656,
        "LastEpoch_Days": 657,
        "Price": 0.108323,
        "Cumulative_Price": 0.110354
    },
    {
        "date": "2023/9/12",
        "lastEpoch": "2023/9/12",
        "return": "  0.000398 ",
        "cum_rtn": "  0.002429 ",
        "rates": "6.61%",
        "TTM_Days": 655,
        "LastEpoch_Days": 655,
        "Price": 0.108448,
        "Cumulative_Price": 0.110877
    },
    {
        "date": "2023/9/13",
        "lastEpoch": "2023/9/12",
        "return": "  -   ",
        "cum_rtn": "  0.002429 ",
        "rates": "6.51%",
        "TTM_Days": 654,
        "LastEpoch_Days": 655,
        "Price": 0.106967,
        "Cumulative_Price": 0.109396
    },
    {
        "date": "2023/9/14",
        "lastEpoch": "2023/9/14",
        "return": "  0.000405 ",
        "cum_rtn": "  0.002834 ",
        "rates": "6.61%",
        "TTM_Days": 653,
        "LastEpoch_Days": 653,
        "Price": 0.108231,
        "Cumulative_Price": 0.111065
    },
    {
        "date": "2023/9/15",
        "lastEpoch": "2023/9/14",
        "return": "  -   ",
        "cum_rtn": "  0.002834 ",
        "rates": "6.62%",
        "TTM_Days": 652,
        "LastEpoch_Days": 653,
        "Price": 0.108384,
        "Cumulative_Price": 0.111218
    },
    {
        "date": "2023/9/16",
        "lastEpoch": "2023/9/16",
        "return": "  0.000405 ",
        "cum_rtn": "  0.003239 ",
        "rates": "6.76%",
        "TTM_Days": 651,
        "LastEpoch_Days": 651,
        "Price": 0.110166,
        "Cumulative_Price": 0.113405
    },
    {
        "date": "2023/9/17",
        "lastEpoch": "2023/9/16",
        "return": "  -   ",
        "cum_rtn": "  0.003239 ",
        "rates": "6.60%",
        "TTM_Days": 650,
        "LastEpoch_Days": 651,
        "Price": 0.107773,
        "Cumulative_Price": 0.111012
    },
    {
        "date": "2023/9/18",
        "lastEpoch": "2023/9/18",
        "return": "  0.000407 ",
        "cum_rtn": "  0.003646 ",
        "rates": "6.71%",
        "TTM_Days": 649,
        "LastEpoch_Days": 649,
        "Price": 0.109117,
        "Cumulative_Price": 0.112763
    },
    {
        "date": "2023/9/19",
        "lastEpoch": "2023/9/18",
        "return": "  -   ",
        "cum_rtn": "  0.003646 ",
        "rates": "6.65%",
        "TTM_Days": 648,
        "LastEpoch_Days": 649,
        "Price": 0.108203,
        "Cumulative_Price": 0.111849
    },
    {
        "date": "2023/9/20",
        "lastEpoch": "2023/9/20",
        "return": "  0.000403 ",
        "cum_rtn": "  0.004048 ",
        "rates": "6.68%",
        "TTM_Days": 647,
        "LastEpoch_Days": 647,
        "Price": 0.108263,
        "Cumulative_Price": 0.112312
    },
    {
        "date": "2023/9/21",
        "lastEpoch": "2023/9/20",
        "return": "  -   ",
        "cum_rtn": "  0.004048 ",
        "rates": "6.82%",
        "TTM_Days": 646,
        "LastEpoch_Days": 647,
        "Price": 0.110373,
        "Cumulative_Price": 0.114422
    },
    {
        "date": "2023/9/22",
        "lastEpoch": "2023/9/20",
        "return": "  -   ",
        "cum_rtn": "  0.004048 ",
        "rates": "6.61%",
        "TTM_Days": 645,
        "LastEpoch_Days": 647,
        "Price": 0.107313,
        "Cumulative_Price": 0.111362
    },
    {
        "date": "2023/9/23",
        "lastEpoch": "2023/9/23",
        "return": "  0.000403 ",
        "cum_rtn": "  0.004452 ",
        "rates": "6.74%",
        "TTM_Days": 644,
        "LastEpoch_Days": 644,
        "Price": 0.108654,
        "Cumulative_Price": 0.113106
    },
    {
        "date": "2023/9/24",
        "lastEpoch": "2023/9/23",
        "return": "  -   ",
        "cum_rtn": "  0.004452 ",
        "rates": "6.71%",
        "TTM_Days": 643,
        "LastEpoch_Days": 644,
        "Price": 0.108228,
        "Cumulative_Price": 0.112679
    },
    {
        "date": "2023/9/25",
        "lastEpoch": "2023/9/25",
        "return": "  0.000401 ",
        "cum_rtn": "  0.004852 ",
        "rates": "6.70%",
        "TTM_Days": 642,
        "LastEpoch_Days": 642,
        "Price": 0.107851,
        "Cumulative_Price": 0.112703
    },
    {
        "date": "2023/9/26",
        "lastEpoch": "2023/9/25",
        "return": "  -   ",
        "cum_rtn": "  0.004852 ",
        "rates": "6.54%",
        "TTM_Days": 641,
        "LastEpoch_Days": 642,
        "Price": 0.105442,
        "Cumulative_Price": 0.110294
    },
    {
        "date": "2023/9/27",
        "lastEpoch": "2023/9/27",
        "return": "  0.000405 ",
        "cum_rtn": "  0.005257 ",
        "rates": "6.63%",
        "TTM_Days": 640,
        "LastEpoch_Days": 640,
        "Price": 0.106491,
        "Cumulative_Price": 0.111748
    },
    {
        "date": "2023/9/28",
        "lastEpoch": "2023/9/27",
        "return": "  -   ",
        "cum_rtn": "  0.005257 ",
        "rates": "6.63%",
        "TTM_Days": 639,
        "LastEpoch_Days": 640,
        "Price": 0.106465,
        "Cumulative_Price": 0.111722
    },
    {
        "date": "2023/9/29",
        "lastEpoch": "2023/9/29",
        "return": "  0.000404 ",
        "cum_rtn": "  0.005661 ",
        "rates": "6.64%",
        "TTM_Days": 638,
        "LastEpoch_Days": 638,
        "Price": 0.106354,
        "Cumulative_Price": 0.112015
    },
    {
        "date": "2023/9/30",
        "lastEpoch": "2023/9/29",
        "return": "  -   ",
        "cum_rtn": "  0.005661 ",
        "rates": "6.50%",
        "TTM_Days": 637,
        "LastEpoch_Days": 638,
        "Price": 0.104202,
        "Cumulative_Price": 0.109863
    },
    {
        "date": "2023/10/1",
        "lastEpoch": "2023/10/1",
        "return": "  0.000401 ",
        "cum_rtn": "  0.006062 ",
        "rates": "6.60%",
        "TTM_Days": 636,
        "LastEpoch_Days": 636,
        "Price": 0.105414,
        "Cumulative_Price": 0.111477
    },
    {
        "date": "2023/10/2",
        "lastEpoch": "2023/10/1",
        "return": "  -   ",
        "cum_rtn": "  0.006062 ",
        "rates": "6.63%",
        "TTM_Days": 635,
        "LastEpoch_Days": 636,
        "Price": 0.105796,
        "Cumulative_Price": 0.111859
    },
    {
        "date": "2023/10/3",
        "lastEpoch": "2023/10/3",
        "return": "  0.000401 ",
        "cum_rtn": "  0.006463 ",
        "rates": "6.58%",
        "TTM_Days": 634,
        "LastEpoch_Days": 634,
        "Price": 0.104735,
        "Cumulative_Price": 0.111198
    },
    {
        "date": "2023/10/4",
        "lastEpoch": "2023/10/3",
        "return": "  -   ",
        "cum_rtn": "  0.006463 ",
        "rates": "6.60%",
        "TTM_Days": 633,
        "LastEpoch_Days": 634,
        "Price": 0.105034,
        "Cumulative_Price": 0.111497
    },
    {
        "date": "2023/10/5",
        "lastEpoch": "2023/10/3",
        "return": "  -   ",
        "cum_rtn": "  0.006463 ",
        "rates": "6.41%",
        "TTM_Days": 632,
        "LastEpoch_Days": 634,
        "Price": 0.102309,
        "Cumulative_Price": 0.108772
    },
    {
        "date": "2023/10/6",
        "lastEpoch": "2023/10/6",
        "return": "  0.000401 ",
        "cum_rtn": "  0.006864 ",
        "rates": "6.41%",
        "TTM_Days": 631,
        "LastEpoch_Days": 631,
        "Price": 0.101901,
        "Cumulative_Price": 0.108764
    },
    {
        "date": "2023/10/7",
        "lastEpoch": "2023/10/6",
        "return": "  -   ",
        "cum_rtn": "  0.006864 ",
        "rates": "6.47%",
        "TTM_Days": 630,
        "LastEpoch_Days": 631,
        "Price": 0.102712,
        "Cumulative_Price": 0.109576
    },
    {
        "date": "2023/10/8",
        "lastEpoch": "2023/10/8",
        "return": "  0.000419 ",
        "cum_rtn": "  0.007283 ",
        "rates": "6.48%",
        "TTM_Days": 629,
        "LastEpoch_Days": 629,
        "Price": 0.102601,
        "Cumulative_Price": 0.109884
    },
    {
        "date": "2023/10/9",
        "lastEpoch": "2023/10/8",
        "return": "  -   ",
        "cum_rtn": "  0.007283 ",
        "rates": "6.40%",
        "TTM_Days": 628,
        "LastEpoch_Days": 629,
        "Price": 0.101413,
        "Cumulative_Price": 0.108696
    },
    {
        "date": "2023/10/10",
        "lastEpoch": "2023/10/10",
        "return": "  0.000397 ",
        "cum_rtn": "  0.007679 ",
        "rates": "6.37%",
        "TTM_Days": 627,
        "LastEpoch_Days": 627,
        "Price": 0.100718,
        "Cumulative_Price": 0.108397
    },
    {
        "date": "2023/10/11",
        "lastEpoch": "2023/10/10",
        "return": "  -   ",
        "cum_rtn": "  0.007679 ",
        "rates": "6.40%",
        "TTM_Days": 626,
        "LastEpoch_Days": 627,
        "Price": 0.101118,
        "Cumulative_Price": 0.108797
    },
    {
        "date": "2023/10/12",
        "lastEpoch": "2023/10/12",
        "return": "  0.000412 ",
        "cum_rtn": "  0.008092 ",
        "rates": "6.40%",
        "TTM_Days": 625,
        "LastEpoch_Days": 625,
        "Price": 0.100735,
        "Cumulative_Price": 0.108826
    },
    {
        "date": "2023/10/13",
        "lastEpoch": "2023/10/12",
        "return": "  -   ",
        "cum_rtn": "  0.008092 ",
        "rates": "6.45%",
        "TTM_Days": 624,
        "LastEpoch_Days": 625,
        "Price": 0.101452,
        "Cumulative_Price": 0.109543
    },
    {
        "date": "2023/10/14",
        "lastEpoch": "2023/10/14",
        "return": "  0.000401 ",
        "cum_rtn": "  0.008493 ",
        "rates": "6.46%",
        "TTM_Days": 623,
        "LastEpoch_Days": 623,
        "Price": 0.101373,
        "Cumulative_Price": 0.109866
    },
    {
        "date": "2023/10/15",
        "lastEpoch": "2023/10/14",
        "return": "  -   ",
        "cum_rtn": "  0.008493 ",
        "rates": "6.42%",
        "TTM_Days": 622,
        "LastEpoch_Days": 623,
        "Price": 0.100739,
        "Cumulative_Price": 0.109232
    },
    {
        "date": "2023/10/16",
        "lastEpoch": "2023/10/16",
        "return": "  0.000392 ",
        "cum_rtn": "  0.008885 ",
        "rates": "6.50%",
        "TTM_Days": 621,
        "LastEpoch_Days": 621,
        "Price": 0.101661,
        "Cumulative_Price": 0.110545
    },
    {
        "date": "2023/10/17",
        "lastEpoch": "2023/10/16",
        "return": "  -   ",
        "cum_rtn": "  0.008885 ",
        "rates": "6.67%",
        "TTM_Days": 620,
        "LastEpoch_Days": 621,
        "Price": 0.104095,
        "Cumulative_Price": 0.11298
    },
    {
        "date": "2023/10/18",
        "lastEpoch": "2023/10/18",
        "return": "  0.000392 ",
        "cum_rtn": "  0.009277 ",
        "rates": "6.67%",
        "TTM_Days": 619,
        "LastEpoch_Days": 619,
        "Price": 0.103716,
        "Cumulative_Price": 0.112993
    },
    {
        "date": "2023/10/19",
        "lastEpoch": "2023/10/18",
        "return": "  -   ",
        "cum_rtn": "  0.009277 ",
        "rates": "6.65%",
        "TTM_Days": 618,
        "LastEpoch_Days": 619,
        "Price": 0.103398,
        "Cumulative_Price": 0.112675
    },
    {
        "date": "2023/10/20",
        "lastEpoch": "2023/10/20",
        "return": "  0.000395 ",
        "cum_rtn": "  0.009672 ",
        "rates": "6.60%",
        "TTM_Days": 617,
        "LastEpoch_Days": 617,
        "Price": 0.10239,
        "Cumulative_Price": 0.112062
    },
    {
        "date": "2023/10/21",
        "lastEpoch": "2023/10/20",
        "return": "  -   ",
        "cum_rtn": "  0.009672 ",
        "rates": "6.68%",
        "TTM_Days": 616,
        "LastEpoch_Days": 617,
        "Price": 0.103606,
        "Cumulative_Price": 0.113278
    },
    {
        "date": "2023/10/22",
        "lastEpoch": "2023/10/22",
        "return": "  0.000393 ",
        "cum_rtn": "  0.010065 ",
        "rates": "6.69%",
        "TTM_Days": 615,
        "LastEpoch_Days": 615,
        "Price": 0.103301,
        "Cumulative_Price": 0.113366
    },
    {
        "date": "2023/10/23",
        "lastEpoch": "2023/10/22",
        "return": "  -   ",
        "cum_rtn": "  0.010065 ",
        "rates": "6.50%",
        "TTM_Days": 614,
        "LastEpoch_Days": 615,
        "Price": 0.100604,
        "Cumulative_Price": 0.110669
    },
    {
        "date": "2023/10/24",
        "lastEpoch": "2023/10/24",
        "return": "  0.000396 ",
        "cum_rtn": "  0.010461 ",
        "rates": "6.67%",
        "TTM_Days": 613,
        "LastEpoch_Days": 613,
        "Price": 0.102808,
        "Cumulative_Price": 0.113268
    },
    {
        "date": "2023/10/25",
        "lastEpoch": "2023/10/24",
        "return": "  -   ",
        "cum_rtn": "  0.010461 ",
        "rates": "6.56%",
        "TTM_Days": 612,
        "LastEpoch_Days": 613,
        "Price": 0.101269,
        "Cumulative_Price": 0.11173
    },
    {
        "date": "2023/10/26",
        "lastEpoch": "2023/10/26",
        "return": "  0.000392 ",
        "cum_rtn": "  0.010853 ",
        "rates": "6.68%",
        "TTM_Days": 611,
        "LastEpoch_Days": 611,
        "Price": 0.102633,
        "Cumulative_Price": 0.113485
    },
    {
        "date": "2023/10/27",
        "lastEpoch": "2023/10/26",
        "return": "  -   ",
        "cum_rtn": "  0.010853 ",
        "rates": "6.60%",
        "TTM_Days": 610,
        "LastEpoch_Days": 611,
        "Price": 0.101435,
        "Cumulative_Price": 0.112288
    },
    {
        "date": "2023/10/28",
        "lastEpoch": "2023/10/28",
        "return": "  0.000386 ",
        "cum_rtn": "  0.011239 ",
        "rates": "6.71%",
        "TTM_Days": 609,
        "LastEpoch_Days": 609,
        "Price": 0.102747,
        "Cumulative_Price": 0.113986
    },
    {
        "date": "2023/10/29",
        "lastEpoch": "2023/10/28",
        "return": "  -   ",
        "cum_rtn": "  0.011239 ",
        "rates": "6.59%",
        "TTM_Days": 608,
        "LastEpoch_Days": 609,
        "Price": 0.101028,
        "Cumulative_Price": 0.112267
    },
    {
        "date": "2023/10/30",
        "lastEpoch": "2023/10/30",
        "return": "  0.000392 ",
        "cum_rtn": "  0.011630 ",
        "rates": "6.75%",
        "TTM_Days": 607,
        "LastEpoch_Days": 607,
        "Price": 0.102888,
        "Cumulative_Price": 0.114518
    },
    {
        "date": "2023/10/31",
        "lastEpoch": "2023/10/30",
        "return": "  -   ",
        "cum_rtn": "  0.011630 ",
        "rates": "6.66%",
        "TTM_Days": 606,
        "LastEpoch_Days": 607,
        "Price": 0.101664,
        "Cumulative_Price": 0.113294
    },
    {
        "date": "2023/11/1",
        "lastEpoch": "2023/10/30",
        "return": "  -   ",
        "cum_rtn": "  0.011630 ",
        "rates": "6.67%",
        "TTM_Days": 605,
        "LastEpoch_Days": 607,
        "Price": 0.101809,
        "Cumulative_Price": 0.113439
    },
    {
        "date": "2023/11/2",
        "lastEpoch": "2023/11/2",
        "return": "  0.000374 ",
        "cum_rtn": "  0.012004 ",
        "rates": "6.69%",
        "TTM_Days": 604,
        "LastEpoch_Days": 604,
        "Price": 0.101588,
        "Cumulative_Price": 0.113593
    },
    {
        "date": "2023/11/3",
        "lastEpoch": "2023/11/2",
        "return": "  -   ",
        "cum_rtn": "  0.012004 ",
        "rates": "6.56%",
        "TTM_Days": 603,
        "LastEpoch_Days": 604,
        "Price": 0.099827,
        "Cumulative_Price": 0.111832
    },
    {
        "date": "2023/11/4",
        "lastEpoch": "2023/11/4",
        "return": "  0.000386 ",
        "cum_rtn": "  0.012390 ",
        "rates": "6.61%",
        "TTM_Days": 602,
        "LastEpoch_Days": 602,
        "Price": 0.10016,
        "Cumulative_Price": 0.11255
    },
    {
        "date": "2023/11/5",
        "lastEpoch": "2023/11/4",
        "return": "  -   ",
        "cum_rtn": "  0.012390 ",
        "rates": "6.48%",
        "TTM_Days": 601,
        "LastEpoch_Days": 602,
        "Price": 0.098356,
        "Cumulative_Price": 0.110746
    },
    {
        "date": "2023/11/6",
        "lastEpoch": "2023/11/6",
        "return": "  0.000394 ",
        "cum_rtn": "  0.012784 ",
        "rates": "6.62%",
        "TTM_Days": 600,
        "LastEpoch_Days": 600,
        "Price": 0.100056,
        "Cumulative_Price": 0.11284
    },
    {
        "date": "2023/11/7",
        "lastEpoch": "2023/11/6",
        "return": "  -   ",
        "cum_rtn": "  0.012784 ",
        "rates": "6.64%",
        "TTM_Days": 599,
        "LastEpoch_Days": 600,
        "Price": 0.100235,
        "Cumulative_Price": 0.113019
    },
    {
        "date": "2023/11/8",
        "lastEpoch": "2023/11/8",
        "return": "  0.000393 ",
        "cum_rtn": "  0.013178 ",
        "rates": "6.65%",
        "TTM_Days": 598,
        "LastEpoch_Days": 598,
        "Price": 0.100157,
        "Cumulative_Price": 0.113335
    },
    {
        "date": "2023/11/9",
        "lastEpoch": "2023/11/8",
        "return": "  -   ",
        "cum_rtn": "  0.013178 ",
        "rates": "6.64%",
        "TTM_Days": 597,
        "LastEpoch_Days": 598,
        "Price": 0.09997,
        "Cumulative_Price": 0.113148
    },
    {
        "date": "2023/11/10",
        "lastEpoch": "2023/11/10",
        "return": "  0.000389 ",
        "cum_rtn": "  0.013566 ",
        "rates": "6.77%",
        "TTM_Days": 596,
        "LastEpoch_Days": 596,
        "Price": 0.10139,
        "Cumulative_Price": 0.114956
    },
    {
        "date": "2023/11/11",
        "lastEpoch": "2023/11/10",
        "return": "  -   ",
        "cum_rtn": "  0.013566 ",
        "rates": "6.69%",
        "TTM_Days": 595,
        "LastEpoch_Days": 596,
        "Price": 0.10035,
        "Cumulative_Price": 0.113916
    },
    {
        "date": "2023/11/12",
        "lastEpoch": "2023/11/12",
        "return": "  0.000390 ",
        "cum_rtn": "  0.013956 ",
        "rates": "6.67%",
        "TTM_Days": 594,
        "LastEpoch_Days": 594,
        "Price": 0.099707,
        "Cumulative_Price": 0.113663
    },
    {
        "date": "2023/11/13",
        "lastEpoch": "2023/11/12",
        "return": "  -   ",
        "cum_rtn": "  0.013956 ",
        "rates": "6.70%",
        "TTM_Days": 593,
        "LastEpoch_Days": 594,
        "Price": 0.100123,
        "Cumulative_Price": 0.114079
    },
    {
        "date": "2023/11/14",
        "lastEpoch": "2023/11/14",
        "return": "  0.000390 ",
        "cum_rtn": "  0.014347 ",
        "rates": "6.54%",
        "TTM_Days": 592,
        "LastEpoch_Days": 592,
        "Price": 0.097653,
        "Cumulative_Price": 0.112
    },
    {
        "date": "2023/11/15",
        "lastEpoch": "2023/11/14",
        "return": "  -   ",
        "cum_rtn": "  0.014347 ",
        "rates": "6.60%",
        "TTM_Days": 591,
        "LastEpoch_Days": 592,
        "Price": 0.098437,
        "Cumulative_Price": 0.112783
    },
    {
        "date": "2023/11/16",
        "lastEpoch": "2023/11/14",
        "return": "  -   ",
        "cum_rtn": "  0.014347 ",
        "rates": "6.44%",
        "TTM_Days": 590,
        "LastEpoch_Days": 592,
        "Price": 0.09624,
        "Cumulative_Price": 0.110587
    },
    {
        "date": "2023/11/17",
        "lastEpoch": "2023/11/17",
        "return": "  0.000399 ",
        "cum_rtn": "  0.014745 ",
        "rates": "6.45%",
        "TTM_Days": 589,
        "LastEpoch_Days": 589,
        "Price": 0.09601,
        "Cumulative_Price": 0.110756
    },
    {
        "date": "2023/11/18",
        "lastEpoch": "2023/11/17",
        "return": "  -   ",
        "cum_rtn": "  0.014745 ",
        "rates": "6.47%",
        "TTM_Days": 588,
        "LastEpoch_Days": 589,
        "Price": 0.096265,
        "Cumulative_Price": 0.11101
    },
    {
        "date": "2023/11/19",
        "lastEpoch": "2023/11/19",
        "return": "  0.000395 ",
        "cum_rtn": "  0.015140 ",
        "rates": "6.49%",
        "TTM_Days": 587,
        "LastEpoch_Days": 587,
        "Price": 0.096141,
        "Cumulative_Price": 0.111282
    },
    {
        "date": "2023/11/20",
        "lastEpoch": "2023/11/19",
        "return": "  -   ",
        "cum_rtn": "  0.015140 ",
        "rates": "6.44%",
        "TTM_Days": 586,
        "LastEpoch_Days": 587,
        "Price": 0.095563,
        "Cumulative_Price": 0.110703
    },
    {
        "date": "2023/11/21",
        "lastEpoch": "2023/11/21",
        "return": "  0.000403 ",
        "cum_rtn": "  0.015543 ",
        "rates": "6.31%",
        "TTM_Days": 585,
        "LastEpoch_Days": 585,
        "Price": 0.093469,
        "Cumulative_Price": 0.109012
    },
    {
        "date": "2023/11/22",
        "lastEpoch": "2023/11/21",
        "return": "  -   ",
        "cum_rtn": "  0.015543 ",
        "rates": "6.43%",
        "TTM_Days": 584,
        "LastEpoch_Days": 585,
        "Price": 0.095101,
        "Cumulative_Price": 0.110644
    },
    {
        "date": "2023/11/23",
        "lastEpoch": "2023/11/23",
        "return": "  0.000400 ",
        "cum_rtn": "  0.015943 ",
        "rates": "6.35%",
        "TTM_Days": 583,
        "LastEpoch_Days": 583,
        "Price": 0.093704,
        "Cumulative_Price": 0.109647
    },
    {
        "date": "2023/11/24",
        "lastEpoch": "2023/11/23",
        "return": "  -   ",
        "cum_rtn": "  0.015943 ",
        "rates": "6.31%",
        "TTM_Days": 582,
        "LastEpoch_Days": 583,
        "Price": 0.093178,
        "Cumulative_Price": 0.109121
    },
    {
        "date": "2023/11/25",
        "lastEpoch": "2023/11/25",
        "return": "  0.000395 ",
        "cum_rtn": "  0.016338 ",
        "rates": "6.41%",
        "TTM_Days": 581,
        "LastEpoch_Days": 581,
        "Price": 0.094132,
        "Cumulative_Price": 0.11047
    },
    {
        "date": "2023/11/26",
        "lastEpoch": "2023/11/25",
        "return": "  -   ",
        "cum_rtn": "  0.016338 ",
        "rates": "6.36%",
        "TTM_Days": 580,
        "LastEpoch_Days": 581,
        "Price": 0.093456,
        "Cumulative_Price": 0.109794
    },
    {
        "date": "2023/11/27",
        "lastEpoch": "2023/11/27",
        "return": "  0.000392 ",
        "cum_rtn": "  0.016730 ",
        "rates": "6.35%",
        "TTM_Days": 579,
        "LastEpoch_Days": 579,
        "Price": 0.093013,
        "Cumulative_Price": 0.109743
    },
    {
        "date": "2023/11/28",
        "lastEpoch": "2023/11/27",
        "return": "  -   ",
        "cum_rtn": "  0.016730 ",
        "rates": "6.13%",
        "TTM_Days": 578,
        "LastEpoch_Days": 579,
        "Price": 0.090024,
        "Cumulative_Price": 0.106754
    },
    {
        "date": "2023/11/29",
        "lastEpoch": "2023/11/29",
        "return": "  0.000131 ",
        "cum_rtn": "  0.016861 ",
        "rates": "6.09%",
        "TTM_Days": 577,
        "LastEpoch_Days": 577,
        "Price": 0.089243,
        "Cumulative_Price": 0.106104
    },
    {
        "date": "2023/11/30",
        "lastEpoch": "2023/11/30",
        "return": "  0.000260 ",
        "cum_rtn": "  0.017121 ",
        "rates": "6.16%",
        "TTM_Days": 576,
        "LastEpoch_Days": 576,
        "Price": 0.090075,
        "Cumulative_Price": 0.107196
    },
    {
        "date": "2023/12/1",
        "lastEpoch": "2023/11/30",
        "return": "  -   ",
        "cum_rtn": "  0.017121 ",
        "rates": "5.95%",
        "TTM_Days": 575,
        "LastEpoch_Days": 576,
        "Price": 0.087225,
        "Cumulative_Price": 0.104345
    },
    {
        "date": "2023/12/2",
        "lastEpoch": "2023/12/2",
        "return": "  0.000394 ",
        "cum_rtn": "  0.017515 ",
        "rates": "5.99%",
        "TTM_Days": 574,
        "LastEpoch_Days": 574,
        "Price": 0.087463,
        "Cumulative_Price": 0.104978
    },
    {
        "date": "2023/12/3",
        "lastEpoch": "2023/12/2",
        "return": "  -   ",
        "cum_rtn": "  0.017515 ",
        "rates": "5.94%",
        "TTM_Days": 573,
        "LastEpoch_Days": 574,
        "Price": 0.086813,
        "Cumulative_Price": 0.104328
    },
    {
        "date": "2023/12/4",
        "lastEpoch": "2023/12/4",
        "return": "  0.000392 ",
        "cum_rtn": "  0.017907 ",
        "rates": "6.04%",
        "TTM_Days": 572,
        "LastEpoch_Days": 572,
        "Price": 0.087875,
        "Cumulative_Price": 0.105782
    },
    {
        "date": "2023/12/5",
        "lastEpoch": "2023/12/4",
        "return": "  -   ",
        "cum_rtn": "  0.017907 ",
        "rates": "5.95%",
        "TTM_Days": 571,
        "LastEpoch_Days": 572,
        "Price": 0.086528,
        "Cumulative_Price": 0.104435
    },
    {
        "date": "2023/12/6",
        "lastEpoch": "2023/12/6",
        "return": "  0.000389 ",
        "cum_rtn": "  0.018296 ",
        "rates": "6.12%",
        "TTM_Days": 570,
        "LastEpoch_Days": 570,
        "Price": 0.088548,
        "Cumulative_Price": 0.106844
    },
    {
        "date": "2023/12/7",
        "lastEpoch": "2023/12/6",
        "return": "  -   ",
        "cum_rtn": "  0.018296 ",
        "rates": "5.98%",
        "TTM_Days": 569,
        "LastEpoch_Days": 570,
        "Price": 0.086752,
        "Cumulative_Price": 0.105048
    },
    {
        "date": "2023/12/8",
        "lastEpoch": "2023/12/8",
        "return": "  0.000393 ",
        "cum_rtn": "  0.018689 ",
        "rates": "6.21%",
        "TTM_Days": 568,
        "LastEpoch_Days": 568,
        "Price": 0.089478,
        "Cumulative_Price": 0.108167
    },
    {
        "date": "2023/12/9",
        "lastEpoch": "2023/12/8",
        "return": "  -   ",
        "cum_rtn": "  0.018689 ",
        "rates": "6.05%",
        "TTM_Days": 567,
        "LastEpoch_Days": 568,
        "Price": 0.087383,
        "Cumulative_Price": 0.106072
    },
    {
        "date": "2023/12/10",
        "lastEpoch": "2023/12/8",
        "return": "  -   ",
        "cum_rtn": "  0.018689 ",
        "rates": "6.04%",
        "TTM_Days": 566,
        "LastEpoch_Days": 568,
        "Price": 0.087229,
        "Cumulative_Price": 0.105918
    },
    {
        "date": "2023/12/11",
        "lastEpoch": "2023/12/11",
        "return": "  0.000373 ",
        "cum_rtn": "  0.019061 ",
        "rates": "6.09%",
        "TTM_Days": 565,
        "LastEpoch_Days": 565,
        "Price": 0.08749,
        "Cumulative_Price": 0.106551
    },
    {
        "date": "2023/12/12",
        "lastEpoch": "2023/12/11",
        "return": "  -   ",
        "cum_rtn": "  0.019061 ",
        "rates": "6.09%",
        "TTM_Days": 564,
        "LastEpoch_Days": 565,
        "Price": 0.087473,
        "Cumulative_Price": 0.106535
    },
    {
        "date": "2023/12/13",
        "lastEpoch": "2023/12/13",
        "return": "  0.000391 ",
        "cum_rtn": "  0.019452 ",
        "rates": "5.80%",
        "TTM_Days": 563,
        "LastEpoch_Days": 563,
        "Price": 0.083247,
        "Cumulative_Price": 0.102699
    },
    {
        "date": "2023/12/14",
        "lastEpoch": "2023/12/13",
        "return": "  -   ",
        "cum_rtn": "  0.019452 ",
        "rates": "5.83%",
        "TTM_Days": 562,
        "LastEpoch_Days": 563,
        "Price": 0.083647,
        "Cumulative_Price": 0.1031
    },
    {
        "date": "2023/12/15",
        "lastEpoch": "2023/12/15",
        "return": "  0.000408 ",
        "cum_rtn": "  0.019860 ",
        "rates": "5.89%",
        "TTM_Days": 561,
        "LastEpoch_Days": 561,
        "Price": 0.084223,
        "Cumulative_Price": 0.104083
    },
    {
        "date": "2023/12/16",
        "lastEpoch": "2023/12/15",
        "return": "  -   ",
        "cum_rtn": "  0.019860 ",
        "rates": "5.90%",
        "TTM_Days": 560,
        "LastEpoch_Days": 561,
        "Price": 0.084404,
        "Cumulative_Price": 0.104264
    },
    {
        "date": "2023/12/17",
        "lastEpoch": "2023/12/17",
        "return": "  0.000406 ",
        "cum_rtn": "  0.020266 ",
        "rates": "5.84%",
        "TTM_Days": 559,
        "LastEpoch_Days": 559,
        "Price": 0.083288,
        "Cumulative_Price": 0.103554
    },
    {
        "date": "2023/12/18",
        "lastEpoch": "2023/12/17",
        "return": "  -   ",
        "cum_rtn": "  0.020266 ",
        "rates": "5.84%",
        "TTM_Days": 558,
        "LastEpoch_Days": 559,
        "Price": 0.083215,
        "Cumulative_Price": 0.103481
    },
    {
        "date": "2023/12/19",
        "lastEpoch": "2023/12/17",
        "return": "  -   ",
        "cum_rtn": "  0.020266 ",
        "rates": "5.71%",
        "TTM_Days": 557,
        "LastEpoch_Days": 559,
        "Price": 0.081522,
        "Cumulative_Price": 0.101788
    },
    {
        "date": "2023/12/20",
        "lastEpoch": "2023/12/20",
        "return": "  0.000418 ",
        "cum_rtn": "  0.020684 ",
        "rates": "5.82%",
        "TTM_Days": 556,
        "LastEpoch_Days": 556,
        "Price": 0.082548,
        "Cumulative_Price": 0.103231
    },
    {
        "date": "2023/12/21",
        "lastEpoch": "2023/12/20",
        "return": "  -   ",
        "cum_rtn": "  0.020684 ",
        "rates": "5.68%",
        "TTM_Days": 555,
        "LastEpoch_Days": 556,
        "Price": 0.080711,
        "Cumulative_Price": 0.101395
    },
    {
        "date": "2023/12/22",
        "lastEpoch": "2023/12/22",
        "return": "  0.000411 ",
        "cum_rtn": "  0.021095 ",
        "rates": "5.57%",
        "TTM_Days": 554,
        "LastEpoch_Days": 554,
        "Price": 0.07898,
        "Cumulative_Price": 0.100075
    },
    {
        "date": "2023/12/23",
        "lastEpoch": "2023/12/22",
        "return": "  -   ",
        "cum_rtn": "  0.021095 ",
        "rates": "5.56%",
        "TTM_Days": 553,
        "LastEpoch_Days": 554,
        "Price": 0.078864,
        "Cumulative_Price": 0.099959
    },
    {
        "date": "2023/12/24",
        "lastEpoch": "2023/12/24",
        "return": "  0.000411 ",
        "cum_rtn": "  0.021506 ",
        "rates": "5.59%",
        "TTM_Days": 552,
        "LastEpoch_Days": 552,
        "Price": 0.078955,
        "Cumulative_Price": 0.100461
    },
    {
        "date": "2023/12/25",
        "lastEpoch": "2023/12/24",
        "return": "  -   ",
        "cum_rtn": "  0.021506 ",
        "rates": "5.63%",
        "TTM_Days": 551,
        "LastEpoch_Days": 552,
        "Price": 0.079431,
        "Cumulative_Price": 0.100937
    },
    {
        "date": "2023/12/26",
        "lastEpoch": "2023/12/24",
        "return": "  -   ",
        "cum_rtn": "  0.021506 ",
        "rates": "5.72%",
        "TTM_Days": 550,
        "LastEpoch_Days": 552,
        "Price": 0.080637,
        "Cumulative_Price": 0.102143
    },
    {
        "date": "2023/12/27",
        "lastEpoch": "2023/12/27",
        "return": "  0.000419 ",
        "cum_rtn": "  0.021925 ",
        "rates": "5.49%",
        "TTM_Days": 549,
        "LastEpoch_Days": 549,
        "Price": 0.077296,
        "Cumulative_Price": 0.099221
    },
    {
        "date": "2023/12/28",
        "lastEpoch": "2023/12/27",
        "return": "  -   ",
        "cum_rtn": "  0.021925 ",
        "rates": "5.65%",
        "TTM_Days": 548,
        "LastEpoch_Days": 549,
        "Price": 0.079278,
        "Cumulative_Price": 0.101203
    },
    {
        "date": "2023/12/29",
        "lastEpoch": "2023/12/29",
        "return": "  0.000417 ",
        "cum_rtn": "  0.022342 ",
        "rates": "5.44%",
        "TTM_Days": 547,
        "LastEpoch_Days": 547,
        "Price": 0.076325,
        "Cumulative_Price": 0.098667
    },
    {
        "date": "2023/12/30",
        "lastEpoch": "2023/12/29",
        "return": "  -   ",
        "cum_rtn": "  0.022342 ",
        "rates": "5.44%",
        "TTM_Days": 546,
        "LastEpoch_Days": 547,
        "Price": 0.076297,
        "Cumulative_Price": 0.098639
    },
    {
        "date": "2023/12/31",
        "lastEpoch": "2023/12/31",
        "return": "  0.000418 ",
        "cum_rtn": "  0.022760 ",
        "rates": "5.47%",
        "TTM_Days": 545,
        "LastEpoch_Days": 545,
        "Price": 0.076428,
        "Cumulative_Price": 0.099188
    },
    {
        "date": "2024/1/1",
        "lastEpoch": "2023/12/31",
        "return": "  -   ",
        "cum_rtn": "  0.022760 ",
        "rates": "5.51%",
        "TTM_Days": 544,
        "LastEpoch_Days": 545,
        "Price": 0.077009,
        "Cumulative_Price": 0.099769
    },
    {
        "date": "2024/1/2",
        "lastEpoch": "2024/1/2",
        "return": "  0.000414 ",
        "cum_rtn": "  0.023174 ",
        "rates": "5.61%",
        "TTM_Days": 543,
        "LastEpoch_Days": 543,
        "Price": 0.078045,
        "Cumulative_Price": 0.10122
    },
    {
        "date": "2024/1/3",
        "lastEpoch": "2024/1/2",
        "return": "  -   ",
        "cum_rtn": "  0.023174 ",
        "rates": "5.63%",
        "TTM_Days": 542,
        "LastEpoch_Days": 543,
        "Price": 0.078259,
        "Cumulative_Price": 0.101433
    },
    {
        "date": "2024/1/4",
        "lastEpoch": "2024/1/2",
        "return": "  -   ",
        "cum_rtn": "  0.023174 ",
        "rates": "5.57%",
        "TTM_Days": 541,
        "LastEpoch_Days": 543,
        "Price": 0.077519,
        "Cumulative_Price": 0.100693
    },
    {
        "date": "2024/1/5",
        "lastEpoch": "2024/1/5",
        "return": "  0.000422 ",
        "cum_rtn": "  0.023596 ",
        "rates": "5.62%",
        "TTM_Days": 540,
        "LastEpoch_Days": 540,
        "Price": 0.077655,
        "Cumulative_Price": 0.101251
    },
    {
        "date": "2024/1/6",
        "lastEpoch": "2024/1/5",
        "return": "  -   ",
        "cum_rtn": "  0.023596 ",
        "rates": "5.75%",
        "TTM_Days": 539,
        "LastEpoch_Days": 540,
        "Price": 0.079337,
        "Cumulative_Price": 0.102933
    },
    {
        "date": "2024/1/7",
        "lastEpoch": "2024/1/7",
        "return": "  0.000437 ",
        "cum_rtn": "  0.024033 ",
        "rates": "5.64%",
        "TTM_Days": 538,
        "LastEpoch_Days": 538,
        "Price": 0.077745,
        "Cumulative_Price": 0.101777
    },
    {
        "date": "2024/1/8",
        "lastEpoch": "2024/1/8",
        "return": "  0.000000 ",
        "cum_rtn": "  0.024033 ",
        "rates": "5.73%",
        "TTM_Days": 537,
        "LastEpoch_Days": 537,
        "Price": 0.078752,
        "Cumulative_Price": 0.102784
    },
    {
        "date": "2024/1/9",
        "lastEpoch": "2024/1/9",
        "return": "  0.000417 ",
        "cum_rtn": "  0.024450 ",
        "rates": "5.61%",
        "TTM_Days": 536,
        "LastEpoch_Days": 536,
        "Price": 0.077003,
        "Cumulative_Price": 0.101452
    },
    {
        "date": "2024/1/10",
        "lastEpoch": "2024/1/9",
        "return": "  -   ",
        "cum_rtn": "  0.024450 ",
        "rates": "5.68%",
        "TTM_Days": 535,
        "LastEpoch_Days": 536,
        "Price": 0.077921,
        "Cumulative_Price": 0.102371
    },
    {
        "date": "2024/1/11",
        "lastEpoch": "2024/1/11",
        "return": "  0.000427 ",
        "cum_rtn": "  0.024877 ",
        "rates": "5.60%",
        "TTM_Days": 534,
        "LastEpoch_Days": 534,
        "Price": 0.076663,
        "Cumulative_Price": 0.10154
    },
    {
        "date": "2024/1/12",
        "lastEpoch": "2024/1/11",
        "return": "  -   ",
        "cum_rtn": "  0.024877 ",
        "rates": "5.61%",
        "TTM_Days": 533,
        "LastEpoch_Days": 534,
        "Price": 0.076787,
        "Cumulative_Price": 0.101664
    },
    {
        "date": "2024/1/13",
        "lastEpoch": "2024/1/11",
        "return": "  -   ",
        "cum_rtn": "  0.024877 ",
        "rates": "5.49%",
        "TTM_Days": 532,
        "LastEpoch_Days": 534,
        "Price": 0.075206,
        "Cumulative_Price": 0.100083
    },
    {
        "date": "2024/1/14",
        "lastEpoch": "2024/1/14",
        "return": "  0.000424 ",
        "cum_rtn": "  0.025301 ",
        "rates": "5.51%",
        "TTM_Days": 531,
        "LastEpoch_Days": 531,
        "Price": 0.075079,
        "Cumulative_Price": 0.10038
    },
    {
        "date": "2024/1/15",
        "lastEpoch": "2024/1/14",
        "return": "  -   ",
        "cum_rtn": "  0.025301 ",
        "rates": "5.56%",
        "TTM_Days": 530,
        "LastEpoch_Days": 531,
        "Price": 0.075738,
        "Cumulative_Price": 0.10104
    },
    {
        "date": "2024/1/16",
        "lastEpoch": "2024/1/16",
        "return": "  0.000435 ",
        "cum_rtn": "  0.025737 ",
        "rates": "5.59%",
        "TTM_Days": 529,
        "LastEpoch_Days": 529,
        "Price": 0.075806,
        "Cumulative_Price": 0.101543
    },
    {
        "date": "2024/1/17",
        "lastEpoch": "2024/1/16",
        "return": "  -   ",
        "cum_rtn": "  0.025737 ",
        "rates": "5.74%",
        "TTM_Days": 528,
        "LastEpoch_Days": 529,
        "Price": 0.077697,
        "Cumulative_Price": 0.103434
    },
    {
        "date": "2024/1/18",
        "lastEpoch": "2024/1/18",
        "return": "  0.000422 ",
        "cum_rtn": "  0.026159 ",
        "rates": "5.92%",
        "TTM_Days": 527,
        "LastEpoch_Days": 527,
        "Price": 0.07964,
        "Cumulative_Price": 0.105799
    },
    {
        "date": "2024/1/19",
        "lastEpoch": "2024/1/18",
        "return": "  -   ",
        "cum_rtn": "  0.026159 ",
        "rates": "5.97%",
        "TTM_Days": 526,
        "LastEpoch_Days": 527,
        "Price": 0.080301,
        "Cumulative_Price": 0.10646
    },
    {
        "date": "2024/1/20",
        "lastEpoch": "2024/1/20",
        "return": "  0.000418 ",
        "cum_rtn": "  0.026577 ",
        "rates": "5.92%",
        "TTM_Days": 525,
        "LastEpoch_Days": 525,
        "Price": 0.079408,
        "Cumulative_Price": 0.105985
    },
    {
        "date": "2024/1/21",
        "lastEpoch": "2024/1/20",
        "return": "  -   ",
        "cum_rtn": "  0.026577 ",
        "rates": "5.95%",
        "TTM_Days": 524,
        "LastEpoch_Days": 525,
        "Price": 0.079788,
        "Cumulative_Price": 0.106365
    },
    {
        "date": "2024/1/22",
        "lastEpoch": "2024/1/22",
        "return": "  0.000415 ",
        "cum_rtn": "  0.026993 ",
        "rates": "6.07%",
        "TTM_Days": 523,
        "LastEpoch_Days": 523,
        "Price": 0.08103,
        "Cumulative_Price": 0.108022
    },
    {
        "date": "2024/1/23",
        "lastEpoch": "2024/1/22",
        "return": "  -   ",
        "cum_rtn": "  0.026993 ",
        "rates": "5.98%",
        "TTM_Days": 522,
        "LastEpoch_Days": 523,
        "Price": 0.079813,
        "Cumulative_Price": 0.106806
    },
    {
        "date": "2024/1/24",
        "lastEpoch": "2024/1/24",
        "return": "  0.000423 ",
        "cum_rtn": "  0.027416 ",
        "rates": "5.96%",
        "TTM_Days": 521,
        "LastEpoch_Days": 521,
        "Price": 0.079337,
        "Cumulative_Price": 0.106753
    },
    {
        "date": "2024/1/25",
        "lastEpoch": "2024/1/24",
        "return": "  -   ",
        "cum_rtn": "  0.027416 ",
        "rates": "5.84%",
        "TTM_Days": 520,
        "LastEpoch_Days": 521,
        "Price": 0.077806,
        "Cumulative_Price": 0.105222
    },
    {
        "date": "2024/1/26",
        "lastEpoch": "2024/1/26",
        "return": "  0.000434 ",
        "cum_rtn": "  0.027849 ",
        "rates": "5.99%",
        "TTM_Days": 519,
        "LastEpoch_Days": 519,
        "Price": 0.07933,
        "Cumulative_Price": 0.107179
    },
    {
        "date": "2024/1/27",
        "lastEpoch": "2024/1/26",
        "return": "  -   ",
        "cum_rtn": "  0.027849 ",
        "rates": "6.04%",
        "TTM_Days": 518,
        "LastEpoch_Days": 519,
        "Price": 0.079964,
        "Cumulative_Price": 0.107813
    },
    {
        "date": "2024/1/28",
        "lastEpoch": "2024/1/28",
        "return": "  0.000426 ",
        "cum_rtn": "  0.028275 ",
        "rates": "6.12%",
        "TTM_Days": 517,
        "LastEpoch_Days": 517,
        "Price": 0.080747,
        "Cumulative_Price": 0.109023
    },
    {
        "date": "2024/1/29",
        "lastEpoch": "2024/1/28",
        "return": "  -   ",
        "cum_rtn": "  0.028275 ",
        "rates": "6.12%",
        "TTM_Days": 516,
        "LastEpoch_Days": 517,
        "Price": 0.080734,
        "Cumulative_Price": 0.10901
    },
    {
        "date": "2024/1/30",
        "lastEpoch": "2024/1/30",
        "return": "  0.000221 ",
        "cum_rtn": "  0.028496 ",
        "rates": "6.27%",
        "TTM_Days": 515,
        "LastEpoch_Days": 515,
        "Price": 0.082185,
        "Cumulative_Price": 0.110681
    },
    {
        "date": "2024/1/31",
        "lastEpoch": "2024/1/31",
        "return": "  0.000197 ",
        "cum_rtn": "  0.028694 ",
        "rates": "6.25%",
        "TTM_Days": 514,
        "LastEpoch_Days": 514,
        "Price": 0.081856,
        "Cumulative_Price": 0.110549
    },
    {
        "date": "2024/2/1",
        "lastEpoch": "2024/1/31",
        "return": "  -   ",
        "cum_rtn": "  0.028694 ",
        "rates": "6.19%",
        "TTM_Days": 513,
        "LastEpoch_Days": 514,
        "Price": 0.081141,
        "Cumulative_Price": 0.109834
    },
    {
        "date": "2024/2/2",
        "lastEpoch": "2024/2/2",
        "return": "  0.000423 ",
        "cum_rtn": "  0.029117 ",
        "rates": "6.28%",
        "TTM_Days": 512,
        "LastEpoch_Days": 512,
        "Price": 0.081916,
        "Cumulative_Price": 0.111033
    },
    {
        "date": "2024/2/3",
        "lastEpoch": "2024/2/2",
        "return": "  -   ",
        "cum_rtn": "  0.029117 ",
        "rates": "6.34%",
        "TTM_Days": 511,
        "LastEpoch_Days": 512,
        "Price": 0.082612,
        "Cumulative_Price": 0.111729
    },
    {
        "date": "2024/2/4",
        "lastEpoch": "2024/2/4",
        "return": "  0.000458 ",
        "cum_rtn": "  0.029575 ",
        "rates": "6.43%",
        "TTM_Days": 510,
        "LastEpoch_Days": 510,
        "Price": 0.083432,
        "Cumulative_Price": 0.113007
    },
    {
        "date": "2024/2/5",
        "lastEpoch": "2024/2/4",
        "return": "  -   ",
        "cum_rtn": "  0.029575 ",
        "rates": "6.54%",
        "TTM_Days": 509,
        "LastEpoch_Days": 510,
        "Price": 0.084657,
        "Cumulative_Price": 0.114232
    },
    {
        "date": "2024/2/6",
        "lastEpoch": "2024/2/6",
        "return": "  0.000417 ",
        "cum_rtn": "  0.029992 ",
        "rates": "6.49%",
        "TTM_Days": 508,
        "LastEpoch_Days": 508,
        "Price": 0.083844,
        "Cumulative_Price": 0.113836
    },
    {
        "date": "2024/2/7",
        "lastEpoch": "2024/2/6",
        "return": "  -   ",
        "cum_rtn": "  0.029992 ",
        "rates": "6.39%",
        "TTM_Days": 507,
        "LastEpoch_Days": 508,
        "Price": 0.082599,
        "Cumulative_Price": 0.112591
    },
    {
        "date": "2024/2/8",
        "lastEpoch": "2024/2/8",
        "return": "  0.000408 ",
        "cum_rtn": "  0.030400 ",
        "rates": "6.42%",
        "TTM_Days": 506,
        "LastEpoch_Days": 506,
        "Price": 0.082663,
        "Cumulative_Price": 0.113063
    },
    {
        "date": "2024/2/9",
        "lastEpoch": "2024/2/8",
        "return": "  -   ",
        "cum_rtn": "  0.030400 ",
        "rates": "6.54%",
        "TTM_Days": 505,
        "LastEpoch_Days": 506,
        "Price": 0.084092,
        "Cumulative_Price": 0.114493
    },
    {
        "date": "2024/2/10",
        "lastEpoch": "2024/2/10",
        "return": "  0.000415 ",
        "cum_rtn": "  0.030815 ",
        "rates": "6.40%",
        "TTM_Days": 504,
        "LastEpoch_Days": 504,
        "Price": 0.08213,
        "Cumulative_Price": 0.112945
    },
    {
        "date": "2024/2/11",
        "lastEpoch": "2024/2/10",
        "return": "  -   ",
        "cum_rtn": "  0.030815 ",
        "rates": "6.51%",
        "TTM_Days": 503,
        "LastEpoch_Days": 504,
        "Price": 0.083457,
        "Cumulative_Price": 0.114272
    },
    {
        "date": "2024/2/12",
        "lastEpoch": "2024/2/12",
        "return": "  0.000418 ",
        "cum_rtn": "  0.031233 ",
        "rates": "6.52%",
        "TTM_Days": 502,
        "LastEpoch_Days": 502,
        "Price": 0.083234,
        "Cumulative_Price": 0.114466
    },
    {
        "date": "2024/2/13",
        "lastEpoch": "2024/2/12",
        "return": "  -   ",
        "cum_rtn": "  0.031233 ",
        "rates": "6.67%",
        "TTM_Days": 501,
        "LastEpoch_Days": 502,
        "Price": 0.085014,
        "Cumulative_Price": 0.116247
    },
    {
        "date": "2024/2/14",
        "lastEpoch": "2024/2/14",
        "return": "  0.000418 ",
        "cum_rtn": "  0.031651 ",
        "rates": "6.60%",
        "TTM_Days": 500,
        "LastEpoch_Days": 500,
        "Price": 0.083854,
        "Cumulative_Price": 0.115505
    },
    {
        "date": "2024/2/15",
        "lastEpoch": "2024/2/14",
        "return": "  -   ",
        "cum_rtn": "  0.031651 ",
        "rates": "6.74%",
        "TTM_Days": 499,
        "LastEpoch_Days": 500,
        "Price": 0.085506,
        "Cumulative_Price": 0.117157
    },
    {
        "date": "2024/2/16",
        "lastEpoch": "2024/2/16",
        "return": "  0.000393 ",
        "cum_rtn": "  0.032044 ",
        "rates": "6.83%",
        "TTM_Days": 498,
        "LastEpoch_Days": 498,
        "Price": 0.086179,
        "Cumulative_Price": 0.118223
    },
    {
        "date": "2024/2/17",
        "lastEpoch": "2024/2/16",
        "return": "  -   ",
        "cum_rtn": "  0.032044 ",
        "rates": "6.78%",
        "TTM_Days": 497,
        "LastEpoch_Days": 498,
        "Price": 0.08561,
        "Cumulative_Price": 0.117654
    },
    {
        "date": "2024/2/18",
        "lastEpoch": "2024/2/16",
        "return": "  -   ",
        "cum_rtn": "  0.032044 ",
        "rates": "6.72%",
        "TTM_Days": 496,
        "LastEpoch_Days": 498,
        "Price": 0.08496,
        "Cumulative_Price": 0.117004
    },
    {
        "date": "2024/2/19",
        "lastEpoch": "2024/2/19",
        "return": "  0.000425 ",
        "cum_rtn": "  0.032469 ",
        "rates": "6.85%",
        "TTM_Days": 495,
        "LastEpoch_Days": 495,
        "Price": 0.085893,
        "Cumulative_Price": 0.118362
    },
    {
        "date": "2024/2/20",
        "lastEpoch": "2024/2/19",
        "return": "  -   ",
        "cum_rtn": "  0.032469 ",
        "rates": "6.70%",
        "TTM_Days": 494,
        "LastEpoch_Days": 495,
        "Price": 0.084179,
        "Cumulative_Price": 0.116648
    },
    {
        "date": "2024/2/21",
        "lastEpoch": "2024/2/21",
        "return": "  0.000422 ",
        "cum_rtn": "  0.032891 ",
        "rates": "6.80%",
        "TTM_Days": 493,
        "LastEpoch_Days": 493,
        "Price": 0.08508,
        "Cumulative_Price": 0.117971
    },
    {
        "date": "2024/2/22",
        "lastEpoch": "2024/2/21",
        "return": "  -   ",
        "cum_rtn": "  0.032891 ",
        "rates": "6.88%",
        "TTM_Days": 492,
        "LastEpoch_Days": 493,
        "Price": 0.085975,
        "Cumulative_Price": 0.118866
    },
    {
        "date": "2024/2/23",
        "lastEpoch": "2024/2/23",
        "return": "  0.000419 ",
        "cum_rtn": "  0.033310 ",
        "rates": "6.74%",
        "TTM_Days": 491,
        "LastEpoch_Days": 491,
        "Price": 0.084033,
        "Cumulative_Price": 0.117343
    },
    {
        "date": "2024/2/24",
        "lastEpoch": "2024/2/23",
        "return": "  -   ",
        "cum_rtn": "  0.033310 ",
        "rates": "6.69%",
        "TTM_Days": 490,
        "LastEpoch_Days": 491,
        "Price": 0.083438,
        "Cumulative_Price": 0.116749
    },
    {
        "date": "2024/2/25",
        "lastEpoch": "2024/2/25",
        "return": "  0.000413 ",
        "cum_rtn": "  0.033724 ",
        "rates": "6.83%",
        "TTM_Days": 489,
        "LastEpoch_Days": 489,
        "Price": 0.084699,
        "Cumulative_Price": 0.118422
    },
    {
        "date": "2024/2/26",
        "lastEpoch": "2024/2/25",
        "return": "  -   ",
        "cum_rtn": "  0.033724 ",
        "rates": "6.70%",
        "TTM_Days": 488,
        "LastEpoch_Days": 489,
        "Price": 0.083258,
        "Cumulative_Price": 0.116982
    },
    {
        "date": "2024/2/27",
        "lastEpoch": "2024/2/27",
        "return": "  0.000411 ",
        "cum_rtn": "  0.034134 ",
        "rates": "6.77%",
        "TTM_Days": 487,
        "LastEpoch_Days": 487,
        "Price": 0.083666,
        "Cumulative_Price": 0.1178
    }
]